Metadata-Version: 2.4
Name: iflow-mcp_joelio_stocky
Version: 1.0.0
Summary: A friendly MCP server for searching royalty-free stock images
Home-page: https://github.com/yourusername/stocky-mcp
Author: Your Name
Author-email: joelio <joelio@example.com>
License: MIT
Project-URL: Homepage, https://github.com/joelio/stocky
Project-URL: Repository, https://github.com/joelio/stocky
Project-URL: Issues, https://github.com/joelio/stocky/issues
Classifier: Development Status :: 4 - Beta
Classifier: Intended Audience :: Developers
Classifier: Topic :: Software Development :: Libraries :: Python Modules
Classifier: License :: OSI Approved :: MIT License
Classifier: Programming Language :: Python :: 3
Classifier: Programming Language :: Python :: 3.8
Classifier: Programming Language :: Python :: 3.9
Classifier: Programming Language :: Python :: 3.10
Classifier: Programming Language :: Python :: 3.11
Classifier: Operating System :: OS Independent
Requires-Python: >=3.8
License-File: LICENSE
Requires-Dist: mcp>=1.0.0
Requires-Dist: pycurl>=7.45.0
Dynamic: author
Dynamic: home-page
Dynamic: license-file
Dynamic: requires-python
